gunshotmatch_reports/__init__.py
gunshotmatch_reports/alignment.py
gunshotmatch_reports/chromatogram.py
gunshotmatch_reports/peaks.py
gunshotmatch_reports/py.typed
gunshotmatch_reports/utils.py
gunshotmatch_reports-0.8.0.dist-info/LICENSE
gunshotmatch_reports-0.8.0.dist-info/METADATA
gunshotmatch_reports-0.8.0.dist-info/WHEEL
gunshotmatch_reports-0.8.0.dist-info/entry_points.txt
gunshotmatch_reports-0.8.0.dist-info/RECORD
