Metadata-Version: 2.2
Name: gunshotmatch-reports
Version: 0.8.0
Summary: PDF Report Generation for GunShotMatch.
Author-email: Dominic Davis-Foster <dominic@davis-foster.co.uk>
License: MIT
Home-page: https://github.com/GunShotMatch/gunshotmatch-reports
Project-URL: Issue Tracker, https://github.com/GunShotMatch/gunshotmatch-reports/issues
Project-URL: Source Code, https://github.com/GunShotMatch/gunshotmatch-reports
Project-URL: Documentation, https://gunshotmatch-reports.readthedocs.io/en/latest
Platform: Windows
Platform: macOS
Platform: Linux
Classifier: License :: OSI Approved :: MIT License
Classifier: Operating System :: OS Independent
Classifier: Programming Language :: Python
Classifier: Programming Language :: Python :: 3 :: Only
Classifier: Programming Language :: Python :: 3.8
Classifier: Programming Language :: Python :: 3.9
Classifier: Programming Language :: Python :: 3.10
Classifier: Programming Language :: Python :: 3.11
Classifier: Programming Language :: Python :: 3.12
Classifier: Programming Language :: Python :: Implementation :: CPython
Classifier: Typing :: Typed
Requires-Python: >=3.8
Requires-Dist: domdf-python-tools>=3.8.0.post2
Requires-Dist: libgunshotmatch>=0.5.0
Requires-Dist: libgunshotmatch-mpl>=0.6.0
Requires-Dist: matplotlib>=3.7.2
Requires-Dist: reportlab>=4.0.9
Requires-Dist: svglib>=1.5.1
